mwa_vcstools-2.1.1.data/scripts/RVM_fit.py
mwa_vcstools-2.1.1.data/scripts/aocal.py
mwa_vcstools-2.1.1.data/scripts/auto_plot.bash
mwa_vcstools-2.1.1.data/scripts/calc_ephem.py
mwa_vcstools-2.1.1.data/scripts/calibrate_vcs.py
mwa_vcstools-2.1.1.data/scripts/check_disk_usage.sh
mwa_vcstools-2.1.1.data/scripts/check_quota.sh
mwa_vcstools-2.1.1.data/scripts/checks.py
mwa_vcstools-2.1.1.data/scripts/cleanup.py
mwa_vcstools-2.1.1.data/scripts/config_vcs.py
mwa_vcstools-2.1.1.data/scripts/create_ics_psrfits.py
mwa_vcstools-2.1.1.data/scripts/create_psrfits.sh
mwa_vcstools-2.1.1.data/scripts/database_vcs.py
mwa_vcstools-2.1.1.data/scripts/find_pulsar_in_obs.py
mwa_vcstools-2.1.1.data/scripts/job_submit.py
mwa_vcstools-2.1.1.data/scripts/mdir.py
mwa_vcstools-2.1.1.data/scripts/mwa_metadb_utils.py
mwa_vcstools-2.1.1.data/scripts/plotFlatTileBeam.py
mwa_vcstools-2.1.1.data/scripts/plotPolarTileBeam.py
mwa_vcstools-2.1.1.data/scripts/plotTiedArrayBeam.py
mwa_vcstools-2.1.1.data/scripts/process_vcs.py
mwa_vcstools-2.1.1.data/scripts/prof_utils.py
mwa_vcstools-2.1.1.data/scripts/recombine.py
mwa_vcstools-2.1.1.data/scripts/rename_corr_output.py
mwa_vcstools-2.1.1.data/scripts/reorder_chans.py
mwa_vcstools-2.1.1.data/scripts/rm.py
mwa_vcstools-2.1.1.data/scripts/rm_synthesis.py
mwa_vcstools-2.1.1.data/scripts/rts2ao.py
mwa_vcstools-2.1.1.data/scripts/sn_flux_est.py
mwa_vcstools-2.1.1.data/scripts/splice.sh
mwa_vcstools-2.1.1.data/scripts/splice_wrapper.py
mwa_vcstools-2.1.1.data/scripts/stickel.py
mwa_vcstools-2.1.1.data/scripts/submit_to_database.py
mwa_vcstools-2.1.1.data/scripts/untar.sh
mwa_vcstools-2.1.1.data/scripts/version.py
mwa_vcstools-2.1.1.data/scripts/zapchan.py
vcstools/__init__.py
vcstools/data_load.py
vcstools/data/MWA_Trcvr_tile_56.csv
vcstools/data/known_repeating_FRBs.csv
vcstools/data/points_of_interest.csv
mwa_vcstools-2.1.1.dist-info/LICENSE
mwa_vcstools-2.1.1.dist-info/METADATA
mwa_vcstools-2.1.1.dist-info/WHEEL
mwa_vcstools-2.1.1.dist-info/top_level.txt
mwa_vcstools-2.1.1.dist-info/RECORD
