Metadata-Version: 2.1
Name: mwa-vcstools
Version: 2.1.1
Summary: Scripts used to process the Murchison Widefield Array's Voltage Capture System data
Home-page: https://github.com/CIRA-Pulsars-and-Transients-Group/vcstools.git
License: UNKNOWN
Platform: UNKNOWN
Requires-Python: >=3.6
Requires-Dist: astropy (>=3.2.3)
Requires-Dist: argparse (>=1.4.0)
Requires-Dist: h5py (>=2.7.1)
Requires-Dist: numpy (>=1.13.3)
Requires-Dist: matplotlib (>=2.1.0)
Requires-Dist: psrqpy (>=1.0.5)
Requires-Dist: mwa-voltage
Requires-Dist: mwa-pb
